perfassess/__init__.py
perfassess/class_performance_assessor.py
perfassess/main.py
perfassess/testor.py
perfassess/parse_argument/__init__.py
perfassess/parse_argument/check_argument.py
perfassess/parse_argument/define_argument.py
perfassess/parse_argument/parse_argument.py
perfassess-0.0.4.dist-info/METADATA
perfassess-0.0.4.dist-info/WHEEL
perfassess-0.0.4.dist-info/entry_points.txt
perfassess-0.0.4.dist-info/licenses/LICENSE
perfassess-0.0.4.dist-info/RECORD
