Metadata-Version: 2.3
Name: perfassess
Version: 0.0.4
Summary: Access the performance of a given function and create plot.
Project-URL: Homepage, https://github.com/FilouPlains/perfassess
Project-URL: Documentation, https://filouplains.github.io/perfassess/
Project-URL: Repository, https://github.com/FilouPlains/perfassess
Author-email: Lucas ROUAUD <lucas.rouaud@gmail.com>
Maintainer-email: Lucas ROUAUD <lucas.rouaud@gmail.com>
License: MIT License
License-File: LICENSE
Keywords: assessor,memory,performance,plot,python,time
Classifier: Development Status :: 3 - Alpha
Classifier: Intended Audience :: Developers
Classifier: License :: OSI Approved :: MIT License
Classifier: Natural Language :: English
Classifier: Programming Language :: Python :: 3.10
Requires-Python: >=3.10
Requires-Dist: numpy
Requires-Dist: plotly
Requires-Dist: pyyaml
Provides-Extra: dev
Requires-Dist: ipython; extra == 'dev'
Requires-Dist: markdown; extra == 'dev'
Requires-Dist: mkdocs; extra == 'dev'
Requires-Dist: mkdocs-autorefs; extra == 'dev'
Requires-Dist: mkdocs-callouts; extra == 'dev'
Requires-Dist: mkdocs-material; extra == 'dev'
Requires-Dist: mkdocs-material-extensions; extra == 'dev'
Requires-Dist: mkdocstrings; extra == 'dev'
Requires-Dist: mkdocstrings-python; extra == 'dev'
Requires-Dist: pylint; extra == 'dev'
Requires-Dist: pytest; extra == 'dev'
